{
  "last_updated": "2026-06-21T12:05:05.372962Z",
  "report_date": "2026-06-20",
  "data_source": "live",
  "locations": {
    "overland_retail": {
      "name": "Overland \u2014 Retail",
      "net_sales": 2425.7,
      "target": 2140.0,
      "labor_pct": 26.51,
      "avg_check": 24.26,
      "sos": null,
      "trans_count": 100,
      "mtd_net_sales": 55560.54,
      "mtd_target": 42800.0,
      "mtd_labor_pct": 27.39,
      "mtd_avg_check": 19.13,
      "mtd_trans_count": 2904
    },
    "overland_catering": {
      "name": "Overland \u2014 Catering",
      "net_sales": 0.0,
      "target": 454.0,
      "labor_pct": null,
      "avg_check": null,
      "sos": null,
      "trans_count": 0,
      "mtd_net_sales": 4758.02,
      "mtd_target": 9080.0,
      "mtd_labor_pct": null,
      "mtd_avg_check": 297.38,
      "mtd_trans_count": 16
    },
    "state": {
      "name": "State Street",
      "net_sales": 1493.47,
      "target": 1744.0,
      "labor_pct": 18.59,
      "avg_check": 20.46,
      "sos": null,
      "trans_count": 73,
      "mtd_net_sales": 34503.25,
      "mtd_target": 34880.0,
      "mtd_labor_pct": 19.6,
      "mtd_avg_check": 18.56,
      "mtd_trans_count": 1859
    },
    "eubank": {
      "name": "Eubank",
      "net_sales": 2157.7,
      "target": 2188.0,
      "labor_pct": 27.77,
      "avg_check": 25.09,
      "sos": null,
      "trans_count": 86,
      "mtd_net_sales": 51537.23,
      "mtd_target": 43760.0,
      "mtd_labor_pct": 24.24,
      "mtd_avg_check": 24.53,
      "mtd_trans_count": 2101
    },
    "rapido": {
      "name": "Rapido",
      "net_sales": 2124.33,
      "target": 1536.0,
      "labor_pct": 21.98,
      "avg_check": 17.56,
      "sos": null,
      "trans_count": 121,
      "mtd_net_sales": 36118.29,
      "mtd_target": 30720.0,
      "mtd_labor_pct": 23.67,
      "mtd_avg_check": 17.52,
      "mtd_trans_count": 2061
    },
    "food_truck": {
      "name": "Overland \u2014 Food Truck",
      "net_sales": 1392.0,
      "target": 902.0,
      "labor_pct": null,
      "avg_check": 14.65,
      "sos": null,
      "trans_count": 95,
      "mtd_net_sales": 51661.0,
      "mtd_target": 18040.0,
      "mtd_labor_pct": null,
      "mtd_avg_check": 19.2,
      "mtd_trans_count": 2690
    }
  }
}